{
	"credit": "Made with Blockbench by Tellio-Ari",
	"textures": {
		"0": "urban_decor:block/picture_frame",
		"2": "urban_decor:block/pink_picture",
		"particle": "urban_decor:block/picture_frame"
	},
	"elements": [
		{
			"from": [3, 2, 13.75],
			"to": [13, 14, 15.75],
			"rotation": {"angle": 0, "axis": "x", "origin": [8, 2, 14.75]},
			"faces": {
				"north": {"uv": [0, 0, 10, 12], "texture": "#2"},
				"east": {"uv": [16, 0, 14, 12], "texture": "#0"},
				"south": {"uv": [0, 0, 10, 12], "texture": "#0"},
				"west": {"uv": [14, 0, 16, 12], "texture": "#0"},
				"up": {"uv": [0, 14, 10, 16], "texture": "#0"},
				"down": {"uv": [0, 16, 10, 14], "texture": "#0"}
			}
		}
	],
	"display": {
		"thirdperson_righthand": {
			"rotation": [75, 45, 0],
			"translation": [0, 2.5, 0],
			"scale": [0.375, 0.375, 0.375]
		},
		"thirdperson_lefthand": {
			"rotation": [75, 45, 0],
			"translation": [0, 2.5, 0],
			"scale": [0.375, 0.375, 0.375]
		},
		"firstperson_righthand": {
			"rotation": [0, 45, 0],
			"scale": [0.4, 0.4, 0.4]
		},
		"firstperson_lefthand": {
			"rotation": [0, 225, 0],
			"scale": [0.4, 0.4, 0.4]
		},
		"ground": {
			"translation": [0, 3, 0],
			"scale": [0.25, 0.25, 0.25]
		},
		"gui": {
			"rotation": [30, 225, 0],
			"scale": [0.625, 0.625, 0.625]
		},
		"fixed": {
			"scale": [0.5, 0.5, 0.5]
		}
	}
}